Metadata-Version: 1.0
Name: iloveig
Version: 0.0.2
Summary: Download images from instagram
Home-page: https://github.com/xwaynec/iloveig
Author: xwaynec
Author-email: xwaynec@gmail.com
License: v0.1.0, 2017.07.13 -- Initial release.
